char_pic/__init__.py
char_pic/start.py
char_pic_wu-0.1.4.dist-info/METADATA
char_pic_wu-0.1.4.dist-info/WHEEL
char_pic_wu-0.1.4.dist-info/top_level.txt
char_pic_wu-0.1.4.dist-info/RECORD
