Metadata-Version: 2.1
Name: char-pic-wu
Version: 0.1.4
Summary: My package description
License: BSD 3-Clause License
Keywords: one,two
Classifier: Framework :: Django
Classifier: Programming Language :: Python :: 3
Requires-Python: >=3.8
Requires-Dist: cowpy
Requires-Dist: importlib-metadata ; python_version <= "3.10.5"
Provides-Extra: pdf
Requires-Dist: ReportLab (>=1.2) ; extra == 'pdf'
Requires-Dist: RXP ; extra == 'pdf'
Provides-Extra: rest
Requires-Dist: docutils (>=0.3) ; extra == 'rest'
Requires-Dist: pack (==1.1,==1.3) ; extra == 'rest'
